[
    {
        "region": "Canada",
        "equipmentname": [
            {
                "id": 1,
                "name": "PVS",
                "count": 5,
                "status": true
            },
            {
                "id": 2,
                "name": "SVS",
                "count": 6,
                "status": false
            },
            {
                "name": "Scanners",
                "count": 9,
                "status": true
            }
        ]
    },
    {
        "region": "USA",
        "equipmentname": [
            {
                "name": "PVS",
                "count": 15,
                "status": true
            },
            {
                "name": "SVS",
                "count": 26,
                "status": true
            },
            {
                "name": "Scanners",
                "count": 19,
                "status": true
            }
        ]
    },
    {
        "region": "India",
        "equipmentname": [
            {
                "name": "PVS",
                "count": 9,
                "status": true
            },
            {
                "name": "SVS",
                "count": 11,
                "status": true
            },
            {
                "name": "Scanners",
                "count": 29,
                "status": true
            }
        ]
    }
]